{
    "format_version": "1.12",
    "minecraft:recipe_shaped": {
        "description": {
            "identifier": "mc:flour_recipe"
        },
        "tags": [
            "mixer"
        ],
        "pattern": [
            "#  ",
            "   ",
            "   "
        ],
        "key": {
            "#": {
                "item": "minecraft:wheat"
            }
        },
        "result": [
            {
                "item": "mc:flour",
                "count": 1
            }
        ]
    }
}